Workbook

Sheet Sheet2
A3: Row Labels
A4: Agra
A5: Ahmedabad
A6: Aligarh
A7: Amritsar
A8: Bengaluru
A9: Bhopal
A10: Bhubaneswar
A11: Chandigarh
A12: Chennai
A13: Dehradun
A14: Delhi
... A40: Grand Total

Sheet Sheet3
A3: Row Labels
A4: C001
A5: Delhi
A6: C002
A7: Mumbai
A8: C003
A9: Gurgaon
A10: C004
A11: Pune
A12: C005
A13: Bengaluru
A14: C006
... A106: Grand Total

Sheet Sheet4
A3: Row Labels | B3: Sum of Total_Revenue | C3: Sum of Profit
A4: <1/5/2025 | C4: 0
A5: Jan | B5: 92000 | C5: 16560
A6: Feb | B6: 110400 | C6: 19872
A7: Mar | B7: 75800 | C7: 13644
A8: Grand Total | B8: 278200 | C8: 50076

Sheet Sheet5
A3: Row Labels | B3: Sum of Total_Revenue | C3: Count of Order_ID
A4: New | B4: 278200 | C4: 50
A5: (blank)
A6: Grand Total | B6: 278200 | C6: 50

Sheet Sheet6
A3: Row Labels | B3: Sum of Total_Revenue | C3: Sum of Profit
A4: Beauty | B4: 33300 | C4: 5994
A5: Electronics | B5: 101900 | C5: 18342
A6: Fashion | B6: 42400 | C6: 7632
A7: Grocery | B7: 24800 | C7: 4464
A8: Home | B8: 75800 | C8: 13644
A9: (blank) | C9: 0
A10: Grand Total | B10: 278200 | C10: 50076

Sheet Sheet1
A1: Customer_ID | B1: Customer_Name | C1: Clean_City | D1: City | E1: Signup_Date | F1: Order_ID | G1: Order_Date | H1: Product_Category | I1: Product_Name | J1: Quantity | K1: Unit_Price | L1: Total_Revenue | M1: Payment_Mode | N1: Cost_Price | O1: Profit | P1: Order_Month | Q1: Order_quarter | R1: Customer Type | S1: High_value_order_Flag | T1: Delivery_Delay | U1: Discount_PT | V1: Cost_Price_PT | W1: PROFIT_TABLE_PT
A2: C001 | B2: Aarav Sharma | C2: =PROPER(TRIM(D2)) -> Delhi | D2: Delhi | E2: 45662 | F2: O1001 | G2: 46082 | H2: Electronics | I2: Wireless Earbuds | J2: 2 | K2: 2500 | L2: 5000 | M2: UPI | N2: =K2*0.8 -> 2000 | O2: =(K2-N2)*J2*(1-0.1) -> 900 | P2: =TEXT(G2,"MMM") -> Mar | Q2: ="Q"&INT((MONTH(G2)-1)/3)+1 -> Q1 | R2: =IF(COUNTIF(A:A,A2)=1,"New","Repeat") -> New | S2: =IF(L2>5000,1,0) -> 0 | T2: =G2-E2 -> 420 | U2: =IF(N2>5000,0.2,0.1) -> 0.1 | V2: =_xlfn.XLOOKUP(I2,Product_Table!A:A,Product_Table!B:B) -> 40000 | W2: =(K2-V2)*J2*(1-U2) -> -67500
A3: C002 | B3: Priya Mehta | C3: =PROPER(TRIM(D3)) -> Mumbai | D3: Mumbai | E3: 45698 | F3: O1002 | G3: 46082 | H3: Fashion | I3: Sneakers | J3: 1 | K3: 3200 | L3: 3200 | M3: Card | N3: =K3*0.8 -> 2560 | O3: =(K3-N3)*J3*(1-0.1) -> 576 | P3: =TEXT(G3,"MMM") -> Mar | Q3: ="Q"&INT((MONTH(G3)-1)/3)+1 -> Q1 | R3: =IF(COUNTIF(A:A,A3)=1,"New","Repeat") -> New | S3: =IF(L3>5000,1,0) -> 0 | T3: =G3-E3 -> 384 | U3: =IF(N3>5000,0.2,0.1) -> 0.1 | V3: =_xlfn.XLOOKUP(I3,Product_Table!A:A,Product_Table!B:B) -> 5000 | W3: =(K3-V3)*J3*(1-U3) -> -1620
A4: C003 | B4: Rohan Gupta | C4: =PROPER(TRIM(D4)) -> Gurgaon | D4: Gurgaon | E4: 45672 | F4: O1003 | G4: 46083 | H4: Home | I4: Blender | J4: 1 | K4: 4500 | L4: 4500 | M4: Net Banking | N4: =K4*0.8 -> 3600 | O4: =(K4-N4)*J4*(1-0.1) -> 810 | P4: =TEXT(G4,"MMM") -> Mar | Q4: ="Q"&INT((MONTH(G4)-1)/3)+1 -> Q1 | R4: =IF(COUNTIF(A:A,A4)=1,"New","Repeat") -> New | S4: =IF(L4>5000,1,0) -> 0 | T4: =G4-E4 -> 411 | U4: =IF(N4>5000,0.2,0.1) -> 0.1 | V4: =_xlfn.XLOOKUP(I4,Product_Table!A:A,Product_Table!B:B) -> 2000 | W4: =(K4-V4)*J4*(1-U4) -> 2250
A5: C004 | B5: Sneha Iyer | C5: =PROPER(TRIM(D5)) -> Pune | D5: Pune | E5: 45717 | F5: O1004 | G5: 46083 | H5: Beauty | I5: Skincare Kit | J5: 3 | K5: 1200 | L5: 3600 | M5: UPI | N5: =K5*0.8 -> 960 | O5: =(K5-N5)*J5*(1-0.1) -> 648 | P5: =TEXT(G5,"MMM") -> Mar | Q5: ="Q"&INT((MONTH(G5)-1)/3)+1 -> Q1 | R5: =IF(COUNTIF(A:A,A5)=1,"New","Repeat") -> New | S5: =IF(L5>5000,1,0) -> 0 | T5: =G5-E5 -> 366 | U5: =IF(N5>5000,0.2,0.1) -> 0.1 | V5: =_xlfn.XLOOKUP(I5,Product_Table!A:A,Product_Table!B:B) -> 5000 | W5: =(K5-V5)*J5*(1-U5) -> -10260
A6: C005 | B6: Aditya Rao | C6: =PROPER(TRIM(D6)) -> Bengaluru | D6: Bengaluru | E6: 45708 | F6: O1005 | G6: 46084 | H6: Electronics | I6: Smartwatch | J6: 1 | K6: 7000 | L6: 7000 | M6: Card | N6: =K6*0.8 -> 5600 | O6: =(K6-N6)*J6*(1-0.1) -> 1260 | P6: =TEXT(G6,"MMM") -> Mar | Q6: ="Q"&INT((MONTH(G6)-1)/3)+1 -> Q1 | R6: =IF(COUNTIF(A:A,A6)=1,"New","Repeat") -> New | S6: =IF(L6>5000,1,0) -> 1 | T6: =G6-E6 -> 376 | U6: =IF(N6>5000,0.2,0.1) -> 0.2 | V6: =_xlfn.XLOOKUP(I6,Product_Table!A:A,Product_Table!B:B) -> 6000 | W6: =(K6-V6)*J6*(1-U6) -> 800
A7: C006 | B7: Neha Kapoor | C7: =PROPER(TRIM(D7)) -> Jaipur | D7: Jaipur | E7: 45679 | F7: O1006 | G7: 46084 | H7: Grocery | I7: Organic Pack | J7: 4 | K7: 800 | L7: 3200 | M7: UPI | N7: =K7*0.8 -> 640 | O7: =(K7-N7)*J7*(1-0.1) -> 576 | P7: =TEXT(G7,"MMM") -> Mar | Q7: ="Q"&INT((MONTH(G7)-1)/3)+1 -> Q1 | R7: =IF(COUNTIF(A:A,A7)=1,"New","Repeat") -> New | S7: =IF(L7>5000,1,0) -> 0 | T7: =G7-E7 -> 405 | U7: =IF(N7>5000,0.2,0.1) -> 0.1 | V7: =_xlfn.XLOOKUP(I7,Product_Table!A:A,Product_Table!B:B) -> 4000 | W7: =(K7-V7)*J7*(1-U7) -> -11520
A8: C007 | B8: Kunal Verma | C8: =PROPER(TRIM(D8)) -> Lucknow | D8: Lucknow | E8: 45721 | F8: O1007 | G8: 46085 | H8: Fashion | I8: Jacket | J8: 1 | K8: 5000 | L8: 5000 | M8: Wallet | N8: =K8*0.8 -> 4000 | O8: =(K8-N8)*J8*(1-0.1) -> 900 | P8: =TEXT(G8,"MMM") -> Mar | Q8: ="Q"&INT((MONTH(G8)-1)/3)+1 -> Q1 | R8: =IF(COUNTIF(A:A,A8)=1,"New","Repeat") -> New | S8: =IF(L8>5000,1,0) -> 0 | T8: =G8-E8 -> 364 | U8: =IF(N8>5000,0.2,0.1) -> 0.1 | V8: =_xlfn.XLOOKUP(I8,Product_Table!A:A,Product_Table!B:B) -> 6000 | W8: =(K8-V8)*J8*(1-U8) -> -900
A9: C008 | B9: Isha Nair | C9: =PROPER(TRIM(D9)) -> Kochi | D9: Kochi | E9: 45716 | F9: O1008 | G9: 46085 | H9: Electronics | I9: Tablet | J9: 1 | K9: 18000 | L9: 18000 | M9: Card | N9: =K9*0.8 -> 14400 | O9: =(K9-N9)*J9*(1-0.1) -> 3240 | P9: =TEXT(G9,"MMM") -> Mar | Q9: ="Q"&INT((MONTH(G9)-1)/3)+1 -> Q1 | R9: =IF(COUNTIF(A:A,A9)=1,"New","Repeat") -> New | S9: =IF(L9>5000,1,0) -> 1 | T9: =G9-E9 -> 369 | U9: =IF(N9>5000,0.2,0.1) -> 0.2 | V9: =_xlfn.XLOOKUP(I9,Product_Table!A:A,Product_Table!B:B) -> 1000 | W9: =(K9-V9)*J9*(1-U9) -> 13600
A10: C009 | B10: Manav Singh | C10: =PROPER(TRIM(D10)) -> Chandigarh | D10: Chandigarh | E10: 45687 | F10: O1009 | G10: 46086 | H10: Home | I10: Vacuum Cleaner | J10: 1 | K10: 8500 | L10: 8500 | M10: UPI | N10: =K10*0.8 -> 6800 | O10: =(K10-N10)*J10*(1-0.1) -> 1530 | P10: =TEXT(G10,"MMM") -> Mar | Q10: ="Q"&INT((MONTH(G10)-1)/3)+1 -> Q1 | R10: =IF(COUNTIF(A:A,A10)=1,"New","Repeat") -> New | S10: =IF(L10>5000,1,0) -> 1 | T10: =G10-E10 -> 399 | U10: =IF(N10>5000,0.2,0.1) -> 0.2 | V10: =_xlfn.XLOOKUP(I10,Product_Table!A:A,Product_Table!B:B) -> 500 | W10: =(K10-V10)*J10*(1-U10) -> 6400
A11: C010 | B11: Ananya Das | C11: =PROPER(TRIM(D11)) -> Kolkata | D11: Kolkata | E11: 45726 | F11: O1010 | G11: 46086 | H11: Beauty | I11: Hair Dryer | J11: 2 | K11: 2200 | L11: 4400 | M11: Card | N11: =K11*0.8 -> 1760 | O11: =(K11-N11)*J11*(1-0.1) -> 792 | P11: =TEXT(G11,"MMM") -> Mar | Q11: ="Q"&INT((MONTH(G11)-1)/3)+1 -> Q1 | R11: =IF(COUNTIF(A:A,A11)=1,"New","Repeat") -> New | S11: =IF(L11>5000,1,0) -> 0 | T11: =G11-E11 -> 360 | U11: =IF(N11>5000,0.2,0.1) -> 0.1 | V11: =_xlfn.XLOOKUP(I11,Product_Table!A:A,Product_Table!B:B) -> 3000 | W11: =(K11-V11)*J11*(1-U11) -> -1440
A12: C011 | B12: Rahul Jain | C12: =PROPER(TRIM(D12)) -> Indore | D12: Indore | E12: 45675 | F12: O1011 | G12: 46087 | H12: Electronics | I12: Bluetooth Speaker | J12: 2 | K12: 3000 | L12: 6000 | M12: UPI | N12: =K12*0.8 -> 2400 | O12: =(K12-N12)*J12*(1-0.1) -> 1080 | P12: =TEXT(G12,"MMM") -> Mar | Q12: ="Q"&INT((MONTH(G12)-1)/3)+1 -> Q1 | R12: =IF(COUNTIF(A:A,A12)=1,"New","Repeat") -> New | S12: =IF(L12>5000,1,0) -> 1 | T12: =G12-E12 -> 412 | U12: =IF(N12>5000,0.2,0.1) -> 0.1 | V12: =_xlfn.XLOOKUP(I12,Product_Table!A:A,Product_Table!B:B) -> 4500 | W12: =(K12-V12)*J12*(1-U12) -> -2700
A13: C012 | B13: Simran Kaur | C13: =PROPER(TRIM(D13)) -> Amritsar | D13: Amritsar | E13: 45702 | F13: O1012 | G13: 46087 | H13: Fashion | I13: Handbag | J13: 1 | K13: 2800 | L13: 2800 | M13: Card | N13: =K13*0.8 -> 2240 | O13: =(K13-N13)*J13*(1-0.1) -> 504 | P13: =TEXT(G13,"MMM") -> Mar | Q13: ="Q"&INT((MONTH(G13)-1)/3)+1 -> Q1 | R13: =IF(COUNTIF(A:A,A13)=1,"New","Repeat") -> New | S13: =IF(L13>5000,1,0) -> 0 | T13: =G13-E13 -> 385 | U13: =IF(N13>5000,0.2,0.1) -> 0.1 | V13: =_xlfn.XLOOKUP(I13,Product_Table!A:A,Product_Table!B:B) -> 2200 | W13: =(K13-V13)*J13*(1-U13) -> 540
... A48: C047 | B48: Rohit Chawla | C48: =PROPER(TRIM(D48)) -> Delhi | D48: Delhi | E48: 45678 | F48: O1047 | G48: 46105 | H48: Electronics | I48: Smart Bulb | J48: 3 | K48: 1200 | L48: 3600 | M48: Card | N48: =K48*0.8 -> 960 | O48: =(K48-N48)*J48*(1-0.1) -> 648 | P48: =TEXT(G48,"MMM") -> Mar | Q48: ="Q"&INT((MONTH(G48)-1)/3)+1 -> Q1 | R48: =IF(COUNTIF(A:A,A48)=1,"New","Repeat") -> New | S48: =IF(L48>5000,1,0) -> 0 | T48: =G48-E48 -> 427 | U48: =IF(N48>5000,0.2,0.1) -> 0.1 | V48: =_xlfn.XLOOKUP(I48,Product_Table!A:A,Product_Table!B:B) -> 4200 | W48: =(K48-V48)*J48*(1-U48) -> -8100
A49: C048 | B49: Kriti Malhotra | C49: =PROPER(TRIM(D49)) -> Gurgaon | D49: Gurgaon | E49: 45701 | F49: O1048 | G49: 46105 | H49: Fashion | I49: Heels | J49: 1 | K49: 4500 | M49: UPI | N49: =K49*0.8 -> 3600 | O49: =(K49-N49)*J49*(1-0.1) -> 810 | P49: =TEXT(G49,"MMM") -> Mar | Q49: ="Q"&INT((MONTH(G49)-1)/3)+1 -> Q1 | R49: =IF(COUNTIF(A:A,A49)=1,"New","Repeat") -> New | S49: =IF(L49>5000,1,0) -> 0 | T49: =G49-E49 -> 404 | U49: =IF(N49>5000,0.2,0.1) -> 0.1 | V49: =_xlfn.XLOOKUP(I49,Product_Table!A:A,Product_Table!B:B) -> 4400 | W49: =(K49-V49)*J49*(1-U49) -> 90
A50: C049 | B50: Faizan Mir | C50: =PROPER(TRIM(D50)) -> Srinagar | D50: Srinagar | E50: 45726 | F50: O1049 | G50: 46106 | H50: Home | I50: Room Heater | J50: 1 | K50: 7500 | L50: 7500 | M50: Net Banking | N50: =K50*0.8 -> 6000 | O50: =(K50-N50)*J50*(1-0.1) -> 1350 | P50: =TEXT(G50,"MMM") -> Mar | Q50: ="Q"&INT((MONTH(G50)-1)/3)+1 -> Q1 | R50: =IF(COUNTIF(A:A,A50)=1,"New","Repeat") -> New | S50: =IF(L50>5000,1,0) -> 1 | T50: =G50-E50 -> 380 | U50: =IF(N50>5000,0.2,0.1) -> 0.2 | V50: =_xlfn.XLOOKUP(I50,Product_Table!A:A,Product_Table!B:B) -> 3300 | W50: =(K50-V50)*J50*(1-U50) -> 3360
A51: C050 | B51: Priti Nanda | C51: =PROPER(TRIM(D51)) -> Raipur | D51: Raipur | E51: 45674 | F51: O1050 | G51: 46106 | H51: Beauty | I51: Body Care Set | J51: 2 | K51: 2100 | L51: 4200 | M51: Card | N51: =K51*0.8 -> 1680 | O51: =(K51-N51)*J51*(1-0.1) -> 756 | P51: =TEXT(G51,"MMM") -> Mar | Q51: ="Q"&INT((MONTH(G51)-1)/3)+1 -> Q1 | R51: =IF(COUNTIF(A:A,A51)=1,"New","Repeat") -> New | S51: =IF(L51>5000,1,0) -> 0 | T51: =G51-E51 -> 432 | U51: =IF(N51>5000,0.2,0.1) -> 0.1 | V51: =_xlfn.XLOOKUP(I51,Product_Table!A:A,Product_Table!B:B) -> 1200 | W51: =(K51-V51)*J51*(1-U51) -> 1620
C52: =PROPER(TRIM(D52)) | P52: =TEXT(G52,"MMM") -> Jan | Q52: ="Q"&INT((MONTH(G52)-1)/3)+1 -> Q1 | V52: =-V54 -> 1200 | W52: =(K52-V52)*J52*(1-U52) -> 0
C53: =PROPER(TRIM(D53)) | O53: =(K53-N53)*J53*(1-0.1) -> 0 | P53: =TEXT(G53,"MMM") -> Jan | Q53: ="Q"&INT((MONTH(G53)-1)/3)+1 -> Q1 | W53: =(K53-V53)*J53*(1-U53) -> 0
C54: =PROPER(TRIM(D54)) | O54: =(K54-N54)*J54*(1-0.1) -> 0 | V54: =-V51 -> -1200 | W54: =(K54-V54)*J54*(1-U54) -> 0

Sheet Product_Table
A1: Product_Name | B1: Cost_Price
A2: Wireless Earbuds | B2: 40000
A3: Sneakers | B3: 5000
A4: Blender | B4: 2000
A5: Skincare Kit | B5: 5000
A6: Smartwatch | B6: 6000
A7: Organic Pack | B7: 4000
A8: Jacket | B8: 6000
A9: Tablet | B9: 1000
A10: Vacuum Cleaner | B10: 500
A11: Hair Dryer | B11: 3000
A12: Bluetooth Speaker | B12: 4500
A13: Handbag | B13: 2200
... A51: Body Care Set | B51: 1200
